xgolib/__init__.py
xgolib/xgolib_dog.py
xgolib/xgolib_rider.py
xgolib-1.4.2.dist-info/METADATA
xgolib-1.4.2.dist-info/WHEEL
xgolib-1.4.2.dist-info/top_level.txt
xgolib-1.4.2.dist-info/RECORD
