Metadata-Version: 2.4
Name: xgolib
Version: 1.4.2
Requires-Dist: pyserial
